gleam/__init__.py
gleam/constants.py
gleam/gaussian_fitting.py
gleam/main.py
gleam/matplotlibparams.py
gleam/plot_gaussian.py
gleam/read_files.py
gleam/spectra_operations.py
astro_gleam-1.4.0.dist-info/entry_points.txt
astro_gleam-1.4.0.dist-info/LICENSE
astro_gleam-1.4.0.dist-info/WHEEL
astro_gleam-1.4.0.dist-info/METADATA
astro_gleam-1.4.0.dist-info/RECORD
